AUTHORS
Changelog
INSTALL
MANIFEST.in
README
TODO
setup.cfg
setup.py
docs/Makefile
docs/changelog.rst
docs/conf.py
docs/index.rst
docs/introduction.rst
docs/.build/doctrees/changelog.doctree
docs/.build/doctrees/environment.pickle
docs/.build/doctrees/index.doctree
docs/.build/doctrees/introduction.doctree
docs/.build/doctrees/reference/durian.event.doctree
docs/.build/doctrees/reference/durian.forms.doctree
docs/.build/doctrees/reference/durian.match.able.doctree
docs/.build/doctrees/reference/durian.match.doctree
docs/.build/doctrees/reference/durian.match.strategy.doctree
docs/.build/doctrees/reference/durian.models.doctree
docs/.build/doctrees/reference/durian.tasks.doctree
docs/.build/doctrees/reference/durian.views.doctree
docs/.build/doctrees/reference/index.doctree
docs/.build/html/.buildinfo
docs/.build/html/changelog.html
docs/.build/html/genindex.html
docs/.build/html/index.html
docs/.build/html/introduction.html
docs/.build/html/modindex.html
docs/.build/html/objects.inv
docs/.build/html/search.html
docs/.build/html/searchindex.js
docs/.build/html/reference/durian.event.html
docs/.build/html/reference/durian.forms.html
docs/.build/html/reference/durian.match.able.html
docs/.build/html/reference/durian.match.html
docs/.build/html/reference/durian.match.strategy.html
docs/.build/html/reference/durian.models.html
docs/.build/html/reference/durian.tasks.html
docs/.build/html/reference/durian.views.html
docs/.build/html/reference/index.html
docs/.build/html/sources/changelog.txt
docs/.build/html/sources/index.txt
docs/.build/html/sources/introduction.txt
docs/.build/html/sources/reference/durian.event.txt
docs/.build/html/sources/reference/durian.forms.txt
docs/.build/html/sources/reference/durian.match.able.txt
docs/.build/html/sources/reference/durian.match.strategy.txt
docs/.build/html/sources/reference/durian.match.txt
docs/.build/html/sources/reference/durian.models.txt
docs/.build/html/sources/reference/durian.tasks.txt
durian.egg-info/PKG-INFO
durian.egg-info/SOURCES.txt
durian.egg-info/dependency_links.txt
durian.egg-info/not-zip-safe
durian.egg-info/requires.txt
durian.egg-info/top_level.txt
