Metadata-Version: 1.0
Name: durian
Version: 0.1.0
Summary: Webhooks for Django **EXPERIMENTAL**
Home-page: http://github.com/ask/durian/
Author: Ask Solem
Author-email: askh@opera.com
License: UNKNOWN
Platform: any
Classifier: Development Status :: 4 - Beta
Classifier: Framework :: Django
Classifier: Environment :: Web Environment
Classifier: Topic :: Internet :: WWW/HTTP
Classifier: Topic :: Communications
Classifier: Intended Audience :: Developers
Classifier: Programming Language :: Python
Classifier: Operating System :: OS Independent
Classifier: License :: OSI Approved :: BSD License
